<Properties StartupConfiguration="{C8467869-22F2-472F-B46B-7D92C81586CB}|Default">
  <MonoDevelop.Ide.ItemProperties.matkalasku PreferredExecutionTarget="MonoDevelop.Default" />
  <MonoDevelop.Ide.Workbench ActiveDocument="Program.cs">
    <Files>
      <File FileName="Program.cs" Line="446" Column="71" IsPinned="True" />
      <File FileName="../matkalaskuCore/matkalaskuLuokat.cs" />
      <File FileName="../matkalaskuCoreTests/matkalaskuTests.cs" Line="12" Column="58" />
    </Files>
  </MonoDevelop.Ide.Workbench>
  <MonoDevelop.Ide.DebuggingService.PinnedWatches />
  <MonoDevelop.Ide.Workspace ActiveConfiguration="Debug" />
  <MonoDevelop.Ide.DebuggingService.Breakpoints>
    <BreakpointStore />
  </MonoDevelop.Ide.DebuggingService.Breakpoints>
  <MultiItemStartupConfigurations />
</Properties>